[
  {
    "id": "3154",
    "nome": "1\u00ba semestre - Turma A",
    "curso_id": "7627",
    "alunos": [
      "4429",
      "6503"
    ],
    "disciplinas": [
      "9464"
    ]
  },
  {
    "id": "7029",
    "nome": "1\u00ba semestre - Turma B",
    "curso_id": "7627",
    "alunos": [],
    "disciplinas": [
      "9464",
      "2544"
    ]
  },
  {
    "id": "2172",
    "nome": "1\u00ba semestre - Turma C",
    "curso_id": "7627",
    "alunos": [],
    "disciplinas": [
      "9464",
      "2544"
    ]
  },
  {
    "id": "6136",
    "nome": "1\u00ba semestre - Turma D",
    "curso_id": "7627",
    "alunos": [],
    "disciplinas": [
      "2544",
      "9464"
    ]
  },
  {
    "id": "2159",
    "nome": "1\u00ba semestre - Turma E",
    "curso_id": "7627",
    "alunos": [],
    "disciplinas": [
      "2544",
      "9464"
    ]
  },
  {
    "id": "7652",
    "nome": "1\u00ba semestre - Turma A",
    "curso_id": "9385",
    "alunos": [],
    "disciplinas": [
      "5422"
    ]
  }
]